{
  "$schema": "https://mintlify.com/docs.json",
  "theme": "maple",
  "name": "Runway Docs",
  "colors": {
    "primary": "#C8A7F2",
    "light": "#FFFFFF",
    "dark": "#171716"
  },
  "favicon": "/runway-icon.svg",
  "navigation": {
    "groups": [
      {
        "group": "Get started",
        "pages": [
          "get-started/start-guide", 
          "get-started/glossary"]
      },
      {
        "group": "Concepts",
        "pages": [
          {
            "group": "Drivers",
            "icon": "chart-mixed-up-circle-dollar",
            "pages": [
              "concepts/drivers/drivers-basics",
              "concepts/drivers/driver-details-pane",
              "concepts/drivers/drill-ins",
              "concepts/drivers/driver-formatting",
              "concepts/drivers/duplicate-remove-delete"
            ]
          },
          {
            "group": "Dimensions",
            "icon": "list",
            "pages": [
              "concepts/dimensions/dimensions-basics",
              "concepts/dimensions/segmenting-drivers"
            ]
          },
          {
            "group": "Databases",
            "icon": "database",
            "pages": [
              "concepts/databases/databases-basics",
              "concepts/databases/filtering-sorting-grouping",
              "concepts/databases/rename-export-delete",
              "concepts/databases/formulas-in-databases",
              "concepts/databases/hris-databases"
            ]
          },
          {
            "group": "Models",
            "icon": "table",
            "pages": [
              "concepts/models/models-basics",
              "concepts/models/grouping-drivers",
              "concepts/models/rename-export-delete"
            ]
          },
          {
            "group": "Pages",
            "icon": "file",
            "pages": [
              "concepts/pages/pages-basics",
              "concepts/pages/charts-block",
              "concepts/pages/drivers-table-block",
              "concepts/pages/database-block",
              "concepts/pages/text-media-block"
            ]
          },
          {
            "group": "Formulas",
            "icon": "function",
            "pages": [
              "concepts/formulas/formulas-basics",
              "concepts/formulas/formulas-syntax",
              "concepts/formulas/functions-operators",
              "concepts/last-close"
            ]
          },
          "concepts/scenarios",
          "concepts/plans",
          "concepts/sidebar"
        ]
      },
      {
        "group": "Data integrations",
        "pages": [
          "integrations/intro-to-integrations",
          "integrations/integrations-directory",
          {
            "group": "Accounting",
            "icon": "receipt",
            "pages": [
              "integrations/accounting/quickbooks-online",
              "integrations/accounting/xero",
              "integrations/accounting/netsuite",
              "integrations/multi-entity-integrations"
            ]
          },
          {
            "group": "HRIS",
            "icon": "people-group",
            "pages": [
              "integrations/hris/rippling",
              "integrations/hris/deel",
              "integrations/hris/justworks",
              "integrations/hris/gusto",
              "integrations/hris/hibob"
            ]
          },
          {
            "group": "Revenue",
            "icon": "dollar-sign",
            "pages": [
              "integrations/revenue/hubspot",
              "integrations/revenue/salesforce",
              "integrations/revenue/stripe"
            ]
          },
          {
            "group": "Data storage",
            "icon": "server",
            "pages": [
              "integrations/data-storage/google-sheets",
              "integrations/data-storage/data-warehouses",
              "integrations/data-storage/shared-directory"
            ]
          },
          "integrations/writing-sql"
        ]
      },
      {
        "group": "Guides",
        "icon": "pen-paintbrush",
        "pages": [
          {
            "group": "Modeling workflows",
            "icon": "calculator",
            "pages": [
              "guides/modeling/lookups",
              "guides/modeling/fx-rate",
              "guides/modeling/seasonal-forecasting",
              "guides/modeling/propagating-sparse-data",
              "guides/modeling/headcount-modeling",
              "guides/modeling/cohorts",
              "guides/modeling/bva",
              "guides/modeling/fixing-errors"
            ]
          },
          {
            "group": "Sharing workflow",
            "icon": "lock",
            "pages": [
              "guides/sharing/user-roles",
              "guides/sharing/access-levels",
              "guides/sharing/data-anonymization"
            ]
          }
        ]
      }
    ]
  },
  "logo": {
    "light": "/logo/runway-logo-light.svg",
    "dark": "/logo/runway-logo-dark.svg"
  },
  "navbar": {
    "links": [
      {
        "label": "Support",
        "href": "mailto:support@runway.com"
      }
    ],
    "primary": {
      "type": "button",
      "label": "Dashboard",
      "href": "https://app.runway.com"
    }
  },
  "footer": {
    "socials": {
      "x": "https://x.com/runwayco",
      "linkedin": "https://linkedin.com/company/runway"
    }
  }
}
